gadjid-0.1.0.dist-info/METADATA
gadjid-0.1.0.dist-info/WHEEL
gadjid-0.1.0.dist-info/license_files/LICENSE
gadjid/example.py
gadjid/__init__.py
gadjid/gadjid.pypy39-pp73-win_amd64.pyd
gadjid-0.1.0.dist-info/RECORD
