Metadata-Version: 2.3
Name: gadjid
Version: 0.1.0
Classifier: Programming Language :: Rust
Classifier: Programming Language :: Python :: Implementation :: CPython
Classifier: Programming Language :: Python :: Implementation :: PyPy
Requires-Dist: numpy
Requires-Dist: pytest ; extra == 'test'
Requires-Dist: scipy ; extra == 'test'
Provides-Extra: test
License-File: LICENSE
Summary: Adjustment Identification Distance: A 𝚐𝚊𝚍𝚓𝚒𝚍 for Causal Structure Learning
Keywords: causality,causal structure learning,graph distance,adjustment
Author: Theo Würtzen, Sebastian Weichwald, Leonard Henckel
License: MPL-2.0
Requires-Python: >=3.8
Project-URL: Bug Tracker, https://github.com/CausalDisco/gadjid/issues
Project-URL: Source Code, https://github.com/CausalDisco/gadjid
Project-URL: arXiv, https://doi.org/10.48550/arXiv.2402.08616
